skelarm/__init__.py
skelarm/canvas.py
skelarm/dynamics.py
skelarm/kinematics.py
skelarm/plotting.py
skelarm/py.typed
skelarm/skeleton.py
skelarm-0.1.0.dist-info/licenses/LICENSE
skelarm-0.1.0.dist-info/WHEEL
skelarm-0.1.0.dist-info/METADATA
skelarm-0.1.0.dist-info/RECORD
