Metadata-Version: 2.4
Name: skelarm
Version: 0.1.0
Summary: A simple dynamics simulator for a configurable planar robot arm.
Keywords: robotics,kinematics,dynamics,simulation,planar,physics
Author: Hiroshi Atsuta
Author-email: Hiroshi Atsuta <atsuta@ieee.org>
License-Expression: GPL-3.0-only
License-File: LICENSE
Classifier: Development Status :: 3 - Alpha
Classifier: Intended Audience :: Developers
Classifier: Intended Audience :: Science/Research
Classifier: License :: OSI Approved :: GNU General Public License v3 (GPLv3)
Classifier: Operating System :: OS Independent
Classifier: Programming Language :: Python :: 3
Classifier: Programming Language :: Python :: 3.12
Classifier: Programming Language :: Python :: 3.13
Classifier: Programming Language :: Python :: 3.14
Classifier: Topic :: Scientific/Engineering :: Physics
Classifier: Typing :: Typed
Requires-Dist: matplotlib>=3.10.7
Requires-Dist: np2typing>=2.6.3
Requires-Dist: numpy>=2.0.0
Requires-Dist: pyqt6>=6.10.1
Requires-Dist: scipy>=1.16.3
Requires-Dist: hypothesis>=6.148.7 ; extra == 'dev'
Requires-Dist: nox>=2025.11.12 ; extra == 'dev'
Requires-Dist: pre-commit>=4.5.0 ; extra == 'dev'
Requires-Dist: pyright>=1.1.407 ; extra == 'dev'
Requires-Dist: pytest>=9.0.2 ; extra == 'dev'
Requires-Dist: pytest-cov>=7.0.0 ; extra == 'dev'
Requires-Dist: pytest-randomly>=4.0.1 ; extra == 'dev'
Requires-Dist: pytest-xdist>=3.8.0 ; extra == 'dev'
Requires-Dist: ruff>=0.14.8 ; extra == 'dev'
Requires-Dist: mkdocs>=1.6.1 ; extra == 'docs'
Requires-Dist: mkdocs-material>=9.5.49 ; extra == 'docs'
Requires-Dist: mkdocstrings[python]>=0.27.0 ; extra == 'docs'
Requires-Dist: pymdown-extensions>=10.13 ; extra == 'docs'
Requires-Python: >=3.12
Project-URL: Documentation, https://hrshtst.github.io/skelarm/
Project-URL: Repository, https://github.com/hrshtst/skelarm
Provides-Extra: dev
Provides-Extra: docs
